lunalib/.gitignore
lunalib/__init__.py
lunalib/cli.py
lunalib/config.py
lunalib/luna_lib.py
lunalib/wallet_manager.py
lunalib/__pycache__/__init__.cpython-310.pyc
lunalib/core/__init__.py
lunalib/core/blockchain.py
lunalib/core/crypto.py
lunalib/core/daemon.py
lunalib/core/daemon_server.py
lunalib/core/mempool.py
lunalib/core/p2p.py
lunalib/core/sm2.py
lunalib/core/sm3.py
lunalib/core/sm4.py
lunalib/core/wallet.py
lunalib/core/wallet_db.py
lunalib/core/wallet_manager.py
lunalib/core/wallet_sync_helper.py
lunalib/core/__pycache__/__init__.cpython-310.pyc
lunalib/core/__pycache__/blockchain.cpython-310.pyc
lunalib/core/__pycache__/crypto.cpython-310.pyc
lunalib/core/__pycache__/mempool.cpython-310.pyc
lunalib/core/__pycache__/wallet.cpython-310.pyc
lunalib/core/sm2_c/__init__.py
lunalib/core/sm2_c/sm2_bn.c
lunalib/core/sm2_c/sm2_bn.h
lunalib/core/sm2_c/sm2_ec.c
lunalib/core/sm2_c/sm2_ec.h
lunalib/core/sm2_c/sm2_ext.c
lunalib/core/sm2_c/sm2_ext.cp310-win_amd64.pyd
lunalib/core/sm2_cuda/__init__.py
lunalib/core/sm2_cuda/sm2_gpu.py
lunalib/core/sm3_c/__init__.py
lunalib/core/sm3_c/sm3_ext.c
lunalib/core/sm3_c/sm3_ext.cp310-win_amd64.pyd
lunalib/core/sm4_cuda/sm4_gpu.py
lunalib/core/sm4_cuda/sm4_kernel.cu
lunalib/gtx/__init__.py
lunalib/gtx/bill_registry.py
lunalib/gtx/digital_bill.py
lunalib/gtx/genesis.py
lunalib/gtx/__pycache__/__init__.cpython-310.pyc
lunalib/gtx/__pycache__/bill_registry.cpython-310.pyc
lunalib/gtx/__pycache__/digital_bill.cpython-310.pyc
lunalib/gtx/__pycache__/genesis.cpython-310.pyc
lunalib/mining/__init__.py
lunalib/mining/cuda_manager.py
lunalib/mining/difficulty.py
lunalib/mining/miner.py
lunalib/mining/__pycache__/__init__.cpython-310.pyc
lunalib/mining/__pycache__/cuda_manager.cpython-310.pyc
lunalib/mining/__pycache__/difficulty.cpython-310.pyc
lunalib/mining/__pycache__/miner.cpython-310.pyc
lunalib/mining/sm3_cuda/sm3_gpu.py
lunalib/mining/sm3_cuda/sm3_kernel.cu
lunalib/mining/sm3_cuda/sm3_kernel_constants.h
lunalib-2.6.6.dist-info/METADATA
lunalib-2.6.6.dist-info/WHEEL
lunalib-2.6.6.dist-info/top_level.txt
lunalib-2.6.6.dist-info/RECORD
