Metadata-Version: 2.4
Name: lunalib
Version: 2.6.6
Summary: Cryptocurrency Ecosystem library (LunaLib) by Sanny and Ling Lin
Home-page: https://github.com/taellinglin/LunaLib
Author-email: taellinglin@gmail.com
Classifier: Programming Language :: Python :: 3
Classifier: License :: OSI Approved :: MIT License
Classifier: Operating System :: OS Independent
Requires-Python: >=3.7
Requires-Dist: requests
Requires-Dist: numpy
Requires-Dist: pytest
Requires-Dist: pytest-benchmark
Requires-Dist: pandas
Requires-Dist: tqdm
Requires-Dist: base58
Requires-Dist: colorama
Requires-Dist: msgpack
Provides-Extra: gpu
Requires-Dist: cupy-cuda12x; python_version < "3.12" and extra == "gpu"
Dynamic: author-email
Dynamic: classifier
Dynamic: description
Dynamic: description-content-type
Dynamic: home-page
Dynamic: provides-extra
Dynamic: requires-dist
Dynamic: requires-python
Dynamic: summary
